colacloud/__init__.py
colacloud/_version.py
colacloud/async_client.py
colacloud/client.py
colacloud/exceptions.py
colacloud/models.py
colacloud/pagination.py
colacloud/py.typed
colacloud-0.1.0.dist-info/METADATA
colacloud-0.1.0.dist-info/WHEEL
colacloud-0.1.0.dist-info/licenses/LICENSE
colacloud-0.1.0.dist-info/RECORD
