Metadata-Version: 2.4
Name: colacloud
Version: 0.1.0
Summary: Python SDK for the COLA Cloud API - Access the TTB COLA Registry of alcohol product label approvals
Project-URL: Homepage, https://colacloud.us
Project-URL: Documentation, https://colacloud.us/docs/api
Project-URL: Repository, https://github.com/cola-cloud-us/colacloud-python
Project-URL: Issues, https://github.com/cola-cloud-us/colacloud-python/issues
Author-email: COLA Cloud <support@colacloud.us>
License-Expression: MIT
License-File: LICENSE
Keywords: alcohol,api,beer,beverages,cola,labels,sdk,spirits,ttb,wine
Classifier: Development Status :: 4 - Beta
Classifier: Intended Audience :: Developers
Classifier: License :: OSI Approved :: MIT License
Classifier: Operating System :: OS Independent
Classifier: Programming Language :: Python :: 3
Classifier: Programming Language :: Python :: 3.10
Classifier: Programming Language :: Python :: 3.11
Classifier: Programming Language :: Python :: 3.12
Classifier: Programming Language :: Python :: 3.13
Classifier: Topic :: Software Development :: Libraries :: Python Modules
Classifier: Typing :: Typed
Requires-Python: >=3.10
Requires-Dist: httpx>=0.25.0
Requires-Dist: pydantic>=2.0.0
Provides-Extra: dev
Requires-Dist: black>=24.0.0; extra == 'dev'
Requires-Dist: isort>=5.13.0; extra == 'dev'
Requires-Dist: mypy>=1.8.0; extra == 'dev'
Requires-Dist: pytest-asyncio>=0.23.0; extra == 'dev'
Requires-Dist: pytest-cov>=4.0.0; extra == 'dev'
Requires-Dist: pytest-httpx>=0.30.0; extra == 'dev'
Requires-Dist: pytest>=8.0.0; extra == 'dev'
Requires-Dist: respx>=0.21.0; extra == 'dev'
